[{"id":"6287797925690@s.whatsapp.net","harimau":-4},{"id":"","harimau":20},{"id":"6287858889824@s.whatsapp.net","harimau":0},{"id":"6283862240453@s.whatsapp.net","harimau":0},{"id":"6283189896572@s.whatsapp.net","harimau":0},{"id":"6282337848271@s.whatsapp.net","harimau":0},{"id":"6288230411750@s.whatsapp.net","harimau":0},{"id":"6289507263740@s.whatsapp.net","harimau":0},{"id":"6281585265724@s.whatsapp.net","harimau":0},{"id":"6288279038600@s.whatsapp.net","harimau":0},{"id":"6282236967935@s.whatsapp.net","harimau":0},{"id":"6285774542623@s.whatsapp.net","harimau":0},{"id":"994404819287@s.whatsapp.net","harimau":0}]